MANIFEST.in
README
setup.py
redsolutioncms.django_seo.egg-info/PKG-INFO
redsolutioncms.django_seo.egg-info/SOURCES.txt
redsolutioncms.django_seo.egg-info/dependency_links.txt
redsolutioncms.django_seo.egg-info/entry_points.txt
redsolutioncms.django_seo.egg-info/not-zip-safe
redsolutioncms.django_seo.egg-info/requires.txt
redsolutioncms.django_seo.egg-info/top_level.txt
seo/__init__.py
seo/admin.py
seo/forms.py
seo/importpath.py
seo/models.py
seo/migrations/0001_initial.py
seo/migrations/0002_auto__add_unique_seo_object_id_content_type.py
seo/migrations/__init__.py
seo/redsolution_setup/__init__.py
seo/redsolution_setup/admin.py
seo/redsolution_setup/make.py
seo/redsolution_setup/models.py
seo/redsolution_setup/templates/seo/redsolutioncms/base_seo.html
seo/redsolution_setup/templates/seo/redsolutioncms/settings.pyt
seo/templatetags/__init__.py
seo/templatetags/seo_tags.py