Metadata-Version: 1.0
Name: redsolutioncms.django-seo
Version: 0.3.5
Summary: Adds generic SEO fields for objects in your site or specific urls
Home-page: UNKNOWN
Author: Alexander Ivanov
Author-email: alexander.ivanov@redsolution.ru
License: GPLv3
Keywords: django seo
Platform: UNKNOWN
Classifier: Development Status :: 3 - Alpha
Classifier: Intended Audience :: Developers
Classifier: License :: OSI Approved :: GNU General Public License (GPL)
Classifier: Framework :: Django
Classifier: Environment :: Web Environment
Classifier: Natural Language :: Russian
Classifier: Natural Language :: English
Classifier: Operating System :: OS Independent
Classifier: Programming Language :: Python
Classifier: Topic :: Internet :: WWW/HTTP :: Indexing/Search
